geoframe/__init__.py
geoframe/geoarrow.py
geoframe/geoframe.py
geoframe/geojson.py
geoframe/geoparquet.py
geoframe/io.py
geoframe-0.2.0.dist-info/licenses/LICENSE
geoframe-0.2.0.dist-info/METADATA
geoframe-0.2.0.dist-info/WHEEL
geoframe-0.2.0.dist-info/top_level.txt
geoframe-0.2.0.dist-info/RECORD
