Metadata-Version: 2.4
Name: geoframe
Version: 0.2.0
Summary: Geospatial Data Management
Author-email: Jayden Rasband <jayden.rasband@gmail.com>
License: MIT
Project-URL: Source, https://github.com/jrasband-dev/geoframe
Project-URL: Changelog, https://github.com/jrasband-dev/geoframe/releases
Project-URL: Tracker, https://github.com/jrasband-dev/geoframe/issues
Project-URL: Contributors, https://github.com/jrasband-dev/geoframe/graphs/contributors
Project-URL: Repository Stats, https://github.com/jrasband-dev/geoframe/pulse
License-File: LICENSE
Requires-Dist: fastkml>=1.1.0
Requires-Dist: polars-extensions
Dynamic: license-file
